timeseries_lib/__init__.py
timeseries_lib/example/__init__.py
timeseries_lib/example/anomalies_example.py
timeseries_lib/example/example.py
timeseries_lib/example/example_lstm.py
timeseries_lib/src/__init__.py
timeseries_lib/src/anomaly_detection.py
timeseries_lib/src/decomposition.py
timeseries_lib/src/forecasting.py
timeseries_lib/src/modeling.py
timeseries_lib/src/smoothing.py
timeseries_lib/src/spectral_analysis.py
timeseries_lib/src/stationarity.py
timeseries_lib/src/visualization.py
timeseries_lib-0.1.7.dist-info/METADATA
timeseries_lib-0.1.7.dist-info/WHEEL
timeseries_lib-0.1.7.dist-info/top_level.txt
timeseries_lib-0.1.7.dist-info/RECORD
